BinaryTimeseries/BinaryTimeseries.py
BinaryTimeseries/Examples.py
BinaryTimeseries/GeneratedApiTests.py
BinaryTimeseries/__init__.py
BinaryTimeseries-1.0.4.dist-info/LICENSE
BinaryTimeseries-1.0.4.dist-info/METADATA
BinaryTimeseries-1.0.4.dist-info/WHEEL
BinaryTimeseries-1.0.4.dist-info/top_level.txt
BinaryTimeseries-1.0.4.dist-info/RECORD
