Metadata-Version: 2.1
Name: BinaryTimeseries
Version: 1.0.4
Summary: A binary timeseries storage format, where the time axis is given via an expression.
Home-page: https://github.com/jonathanschilling/BinaryTimeseries
Author: Jonathan Schilling
Author-email: jonathan.schilling@mail.de
License: UNKNOWN
Platform: UNKNOWN
Classifier: Programming Language :: Python :: 3
Classifier: License :: OSI Approved :: Apache Software License
Classifier: Operating System :: OS Independent
Requires-Python: >=3
Requires-Dist: numpy
